{
    "btc": {
        "conn_1": {
            "rx": {
                "KB_per_cpu_second": "351034.78",
                "accept": "192.168.46.15",
                "buflen": "65536",
                "calls_per_sec": "5414.30",
                "cpu": "4%",
                "cpu_seconds": "16.85",
                "elapsed": "6:00",
                "io": "0+18pf",
                "io_calls": "1950351",
                "megabytes": "5775.9800",
                "memory": "0i+0d-298maxrss",
                "mode": "tcp",
                "msec_per_call": "0.19",
                "nstream": "1",
                "port": "7231",
                "rate_KBps": "16419.33",
                "rate_Mbps": "134.5071",
                "real_seconds": "360.22",
                "receive_window_avail": "43690",
                "receive_window_size": "87380",
                "send_window_avail": "12020",
                "send_window_size": "24040",
                "stats": "cpu",
                "swaps": "1876402+105csw",
                "system": "16.1",
                "user": "0.7"
            },
            "tx": {
                "buflen": "65536",
                "calls_per_sec": "256.71",
                "connect": "192.168.46.11",
                "cpu": "0%",
                "elapsed": "6:00",
                "host": "192.168.46.11",
                "io": "0+3pf",
                "io_calls": "92416",
                "megabytes": "5775.9800",
                "memory": "0i+0d-780maxrss",
                "mode": "tcp",
                "msec_per_call": "3.99",
                "mss": "1448",
                "nstream": "1",
                "port": "7231",
                "rate_KBps": "16429.45",
                "rate_Mbps": "134.5901",
                "real_seconds": "360.00",
                "receive_window_avail": "43690",
                "receive_window_size": "87380",
                "retrans": "0",
                "rtt_ms": "0.433",
                "send_window_avail": "12020",
                "send_window_size": "24040",
                "stats": "cpu",
                "swaps": "4269+39csw",
                "system": "2.8",
                "time_limit": "360.00",
                "user": "0.0"
            }
        },
        "conn_10": {
            "rx": {
                "KB_per_cpu_second": "349013.15",
                "accept": "192.168.46.15",
                "buflen": "65536",
                "calls_per_sec": "1815.90",
                "cpu": "1%",
                "cpu_seconds": "5.68",
                "elapsed": "6:00",
                "io": "0+18pf",
                "io_calls": "654469",
                "megabytes": "1934.6896",
                "memory": "0i+0d-300maxrss",
                "mode": "tcp",
                "msec_per_call": "0.56",
                "nstream": "1",
                "port": "7111",
                "rate_KBps": "5496.85",
                "rate_Mbps": "45.0302",
                "real_seconds": "360.41",
                "receive_window_avail": "43690",
                "receive_window_size": "87380",
                "send_window_avail": "12020",
                "send_window_size": "24040",
                "stats": "cpu",
                "swaps": "631599+6csw",
                "system": "5.3",
                "user": "0.3"
            },
            "tx": {
                "buflen": "65536",
                "calls_per_sec": "85.99",
                "connect": "192.168.46.11",
                "cpu": "0%",
                "elapsed": "6:00",
                "host": "192.168.46.11",
                "io": "0+3pf",
                "io_calls": "30956",
                "megabytes": "1934.6896",
                "memory": "0i+0d-780maxrss",
                "mode": "tcp",
                "msec_per_call": "11.91",
                "mss": "1448",
                "nstream": "1",
                "port": "7111",
                "rate_KBps": "5503.12",
                "rate_Mbps": "45.0815",
                "real_seconds": "360.00",
                "receive_window_avail": "43690",
                "receive_window_size": "87380",
                "retrans": "0",
                "rtt_ms": "0.235",
                "send_window_avail": "12020",
                "send_window_size": "24040",
                "stats": "cpu",
                "swaps": "1470+2csw",
                "system": "1.0",
                "time_limit": "360.00",
                "user": "0.0"
            }
        },
        "conn_11": {
            "rx": {
                "KB_per_cpu_second": "369224.20",
                "accept": "192.168.46.15",
                "buflen": "65536",
                "calls_per_sec": "1839.46",
                "cpu": "1%",
                "cpu_seconds": "5.40",
                "elapsed": "6:00",
                "io": "0+18pf",
                "io_calls": "662754",
                "megabytes": "1948.6446",
                "memory": "0i+0d-300maxrss",
                "mode": "tcp",
                "msec_per_call": "0.56",
                "nstream": "1",
                "port": "7211",
                "rate_KBps": "5538.22",
                "rate_Mbps": "45.3691",
                "real_seconds": "360.30",
                "receive_window_avail": "43690",
                "receive_window_size": "87380",
                "send_window_avail": "12020",
                "send_window_size": "24040",
                "stats": "cpu",
                "swaps": "640892+73csw",
                "system": "5.2",
                "user": "0.1"
            },
            "tx": {
                "buflen": "65536",
                "calls_per_sec": "86.61",
                "connect": "192.168.46.11",
                "cpu": "0%",
                "elapsed": "6:00",
                "host": "192.168.46.11",
                "io": "0+3pf",
                "io_calls": "31179",
                "megabytes": "1948.6446",
                "memory": "0i+0d-782maxrss",
                "mode": "tcp",
                "msec_per_call": "11.82",
                "mss": "1448",
                "nstream": "1",
                "port": "7211",
                "rate_KBps": "5542.81",
                "rate_Mbps": "45.4067",
                "real_seconds": "360.00",
                "receive_window_avail": "43690",
                "receive_window_size": "87380",
                "retrans": "0",
                "rtt_ms": "12.517",
                "send_window_avail": "12020",
                "send_window_size": "24040",
                "stats": "cpu",
                "swaps": "1472+0csw",
                "system": "1.0",
                "time_limit": "360.00",
                "user": "0.0"
            }
        },
        "conn_12": {
            "rx": {
                "KB_per_cpu_second": "374302.24",
                "accept": "192.168.46.15",
                "buflen": "65536",
                "calls_per_sec": "1815.79",
                "cpu": "1%",
                "cpu_seconds": "5.32",
                "elapsed": "6:00",
                "io": "0+18pf",
                "io_calls": "654426",
                "megabytes": "1944.7385",
                "memory": "0i+0d-300maxrss",
                "mode": "tcp",
                "msec_per_call": "0.56",
                "nstream": "1",
                "port": "7141",
                "rate_KBps": "5525.44",
                "rate_Mbps": "45.2644",
                "real_seconds": "360.41",
                "receive_window_avail": "43690",
                "receive_window_size": "87380",
                "send_window_avail": "12020",
                "send_window_size": "24040",
                "stats": "cpu",
                "swaps": "634939+13csw",
                "system": "5.1",
                "user": "0.1"
            },
            "tx": {
                "buflen": "65536",
                "calls_per_sec": "86.43",
                "connect": "192.168.46.11",
                "cpu": "0%",
                "elapsed": "6:00",
                "host": "192.168.46.11",
                "io": "0+3pf",
                "io_calls": "31116",
                "megabytes": "1944.7385",
                "memory": "0i+0d-780maxrss",
                "mode": "tcp",
                "msec_per_call": "11.85",
                "mss": "1448",
                "nstream": "1",
                "port": "7141",
                "rate_KBps": "5531.70",
                "rate_Mbps": "45.3157",
                "real_seconds": "360.00",
                "receive_window_avail": "43690",
                "receive_window_size": "87380",
                "retrans": "0",
                "rtt_ms": "3.796",
                "send_window_avail": "12020",
                "send_window_size": "24040",
                "stats": "cpu",
                "swaps": "1466+50csw",
                "system": "0.9",
                "time_limit": "360.00",
                "user": "0.0"
            }
        },
        "conn_13": {
            "rx": {
                "KB_per_cpu_second": "400576.14",
                "accept": "192.168.46.15",
                "buflen": "65536",
                "calls_per_sec": "1787.53",
                "cpu": "1%",
                "cpu_seconds": "4.90",
                "elapsed": "6:00",
                "io": "0+18pf",
                "io_calls": "644098",
                "megabytes": "1915.3744",
                "memory": "0i+0d-300maxrss",
                "mode": "tcp",
                "msec_per_call": "0.57",
                "nstream": "1",
                "port": "7221",
                "rate_KBps": "5443.21",
                "rate_Mbps": "44.5908",
                "real_seconds": "360.33",
                "receive_window_avail": "43690",
                "receive_window_size": "87380",
                "send_window_avail": "12020",
                "send_window_size": "24040",
                "stats": "cpu",
                "swaps": "626016+74csw",
                "system": "4.7",
                "user": "0.1"
            },
            "tx": {
                "buflen": "65536",
                "calls_per_sec": "85.13",
                "connect": "192.168.46.11",
                "cpu": "0%",
                "elapsed": "6:00",
                "host": "192.168.46.11",
                "io": "0+3pf",
                "io_calls": "30646",
                "megabytes": "1915.3744",
                "memory": "0i+0d-776maxrss",
                "mode": "tcp",
                "msec_per_call": "12.03",
                "mss": "1448",
                "nstream": "1",
                "port": "7221",
                "rate_KBps": "5448.18",
                "rate_Mbps": "44.6315",
                "real_seconds": "360.00",
                "receive_window_avail": "43690",
                "receive_window_size": "87380",
                "retrans": "0",
                "rtt_ms": "6.808",
                "send_window_avail": "12020",
                "send_window_size": "24040",
                "stats": "cpu",
                "swaps": "1436+69csw",
                "system": "0.8",
                "time_limit": "360.00",
                "user": "0.0"
            }
        },
        "conn_14": {
            "rx": {
                "KB_per_cpu_second": "378318.35",
                "accept": "192.168.46.15",
                "buflen": "65536",
                "calls_per_sec": "1766.22",
                "cpu": "1%",
                "cpu_seconds": "5.12",
                "elapsed": "6:00",
                "io": "0+18pf",
                "io_calls": "636643",
                "megabytes": "1890.2318",
                "memory": "0i+0d-300maxrss",
                "mode": "tcp",
                "msec_per_call": "0.58",
                "nstream": "1",
                "port": "7121",
                "rate_KBps": "5369.88",
                "rate_Mbps": "43.9901",
                "real_seconds": "360.45",
                "receive_window_avail": "43690",
                "receive_window_size": "87380",
                "send_window_avail": "12020",
                "send_window_size": "24040",
                "stats": "cpu",
                "swaps": "619054+42csw",
                "system": "4.9",
                "user": "0.1"
            },
            "tx": {
                "buflen": "65536",
                "calls_per_sec": "84.01",
                "connect": "192.168.46.11",
                "cpu": "0%",
                "elapsed": "6:00",
                "host": "192.168.46.11",
                "io": "0+3pf",
                "io_calls": "30244",
                "megabytes": "1890.2318",
                "memory": "0i+0d-780maxrss",
                "mode": "tcp",
                "msec_per_call": "12.19",
                "mss": "1448",
                "nstream": "1",
                "port": "7121",
                "rate_KBps": "5376.66",
                "rate_Mbps": "44.0456",
                "real_seconds": "360.00",
                "receive_window_avail": "43690",
                "receive_window_size": "87380",
                "retrans": "0",
                "rtt_ms": "0.134",
                "send_window_avail": "12020",
                "send_window_size": "24040",
                "stats": "cpu",
                "swaps": "1431+39csw",
                "system": "0.8",
                "time_limit": "360.00",
                "user": "0.0"
            }
        },
        "conn_15": {
            "rx": {
                "KB_per_cpu_second": "365058.13",
                "accept": "192.168.46.15",
                "buflen": "65536",
                "calls_per_sec": "1813.24",
                "cpu": "1%",
                "cpu_seconds": "5.42",
                "elapsed": "6:00",
                "io": "0+18pf",
                "io_calls": "653548",
                "megabytes": "1932.3618",
                "memory": "0i+0d-302maxrss",
                "mode": "tcp",
                "msec_per_call": "0.56",
                "nstream": "1",
                "port": "7181",
                "rate_KBps": "5489.93",
                "rate_Mbps": "44.9735",
                "real_seconds": "360.43",
                "receive_window_avail": "43690",
                "receive_window_size": "87380",
                "send_window_avail": "12020",
                "send_window_size": "24040",
                "stats": "cpu",
                "swaps": "632453+46csw",
                "system": "5.1",
                "user": "0.2"
            },
            "tx": {
                "buflen": "65536",
                "calls_per_sec": "85.88",
                "connect": "192.168.46.11",
                "cpu": "0%",
                "elapsed": "6:00",
                "host": "192.168.46.11",
                "io": "0+3pf",
                "io_calls": "30918",
                "megabytes": "1932.3618",
                "memory": "0i+0d-784maxrss",
                "mode": "tcp",
                "msec_per_call": "11.92",
                "mss": "1448",
                "nstream": "1",
                "port": "7181",
                "rate_KBps": "5496.50",
                "rate_Mbps": "45.0273",
                "real_seconds": "360.00",
                "receive_window_avail": "43690",
                "receive_window_size": "87380",
                "retrans": "0",
                "rtt_ms": "0.342",
                "send_window_avail": "12020",
                "send_window_size": "24040",
                "stats": "cpu",
                "swaps": "1469+11csw",
                "system": "0.9",
                "time_limit": "360.00",
                "user": "0.0"
            }
        },
        "conn_2": {
            "rx": {
                "KB_per_cpu_second": "410787.14",
                "accept": "192.168.46.15",
                "buflen": "65536",
                "calls_per_sec": "5409.40",
                "cpu": "3%",
                "cpu_seconds": "14.40",
                "elapsed": "6:00",
                "io": "0+18pf",
                "io_calls": "1948621",
                "megabytes": "5775.4502",
                "memory": "0i+0d-300maxrss",
                "mode": "tcp",
                "msec_per_call": "0.19",
                "nstream": "1",
                "port": "7201",
                "rate_KBps": "16417.52",
                "rate_Mbps": "134.4923",
                "real_seconds": "360.23",
                "receive_window_avail": "43690",
                "receive_window_size": "87380",
                "send_window_avail": "12020",
                "send_window_size": "24040",
                "stats": "cpu",
                "swaps": "1876193+176csw",
                "system": "13.9",
                "user": "0.4"
            },
            "tx": {
                "buflen": "65536",
                "calls_per_sec": "256.69",
                "connect": "192.168.46.11",
                "cpu": "0%",
                "elapsed": "6:00",
                "host": "192.168.46.11",
                "io": "0+3pf",
                "io_calls": "92408",
                "megabytes": "5775.4502",
                "memory": "0i+0d-776maxrss",
                "mode": "tcp",
                "msec_per_call": "3.99",
                "mss": "1448",
                "nstream": "1",
                "port": "7201",
                "rate_KBps": "16427.95",
                "rate_Mbps": "134.5777",
                "real_seconds": "360.00",
                "receive_window_avail": "43690",
                "receive_window_size": "87380",
                "retrans": "0",
                "rtt_ms": "0.203",
                "send_window_avail": "12020",
                "send_window_size": "24040",
                "stats": "cpu",
                "swaps": "4275+40csw",
                "system": "2.9",
                "time_limit": "360.00",
                "user": "0.0"
            }
        },
        "conn_3": {
            "rx": {
                "KB_per_cpu_second": "357599.22",
                "accept": "192.168.46.15",
                "buflen": "65536",
                "calls_per_sec": "2809.04",
                "cpu": "2%",
                "cpu_seconds": "8.60",
                "elapsed": "6:00",
                "io": "0+18pf",
                "io_calls": "1012258",
                "megabytes": "3002.0650",
                "memory": "0i+0d-300maxrss",
                "mode": "tcp",
                "msec_per_call": "0.36",
                "nstream": "1",
                "port": "7131",
                "rate_KBps": "8530.76",
                "rate_Mbps": "69.8840",
                "real_seconds": "360.36",
                "receive_window_avail": "43690",
                "receive_window_size": "87380",
                "send_window_avail": "12020",
                "send_window_size": "24040",
                "stats": "cpu",
                "swaps": "982325+49csw",
                "system": "8.2",
                "user": "0.3"
            },
            "tx": {
                "buflen": "65536",
                "calls_per_sec": "133.43",
                "connect": "192.168.46.11",
                "cpu": "0%",
                "elapsed": "6:00",
                "host": "192.168.46.11",
                "io": "0+3pf",
                "io_calls": "48034",
                "megabytes": "3002.0650",
                "memory": "0i+0d-780maxrss",
                "mode": "tcp",
                "msec_per_call": "7.67",
                "mss": "1448",
                "nstream": "1",
                "port": "7131",
                "rate_KBps": "8539.21",
                "rate_Mbps": "69.9532",
                "real_seconds": "360.00",
                "receive_window_avail": "43690",
                "receive_window_size": "87380",
                "retrans": "0",
                "rtt_ms": "0.280",
                "send_window_avail": "12020",
                "send_window_size": "24040",
                "stats": "cpu",
                "swaps": "2238+33csw",
                "system": "1.3",
                "time_limit": "360.00",
                "user": "0.0"
            }
        },
        "conn_4": {
            "rx": {
                "KB_per_cpu_second": "354766.04",
                "accept": "192.168.46.15",
                "buflen": "65536",
                "calls_per_sec": "2745.06",
                "cpu": "2%",
                "cpu_seconds": "8.45",
                "elapsed": "6:00",
                "io": "0+18pf",
                "io_calls": "989099",
                "megabytes": "2928.3882",
                "memory": "0i+0d-300maxrss",
                "mode": "tcp",
                "msec_per_call": "0.37",
                "nstream": "1",
                "port": "7191",
                "rate_KBps": "8322.25",
                "rate_Mbps": "68.1759",
                "real_seconds": "360.32",
                "receive_window_avail": "43690",
                "receive_window_size": "87380",
                "send_window_avail": "12020",
                "send_window_size": "24040",
                "stats": "cpu",
                "swaps": "954406+60csw",
                "system": "8.1",
                "user": "0.3"
            },
            "tx": {
                "buflen": "65536",
                "calls_per_sec": "130.15",
                "connect": "192.168.46.11",
                "cpu": "0%",
                "elapsed": "6:00",
                "host": "192.168.46.11",
                "io": "0+3pf",
                "io_calls": "46855",
                "megabytes": "2928.3882",
                "memory": "0i+0d-778maxrss",
                "mode": "tcp",
                "msec_per_call": "7.87",
                "mss": "1448",
                "nstream": "1",
                "port": "7191",
                "rate_KBps": "8329.64",
                "rate_Mbps": "68.2364",
                "real_seconds": "360.00",
                "receive_window_avail": "43690",
                "receive_window_size": "87380",
                "retrans": "0",
                "rtt_ms": "0.212",
                "send_window_avail": "12020",
                "send_window_size": "24040",
                "stats": "cpu",
                "swaps": "2197+27csw",
                "system": "1.3",
                "time_limit": "360.00",
                "user": "0.0"
            }
        },
        "conn_5": {
            "rx": {
                "KB_per_cpu_second": "351839.60",
                "accept": "192.168.46.15",
                "buflen": "65536",
                "calls_per_sec": "2668.12",
                "cpu": "2%",
                "cpu_seconds": "8.29",
                "elapsed": "6:00",
                "io": "0+18pf",
                "io_calls": "961340",
                "megabytes": "2849.2538",
                "memory": "0i+0d-300maxrss",
                "mode": "tcp",
                "msec_per_call": "0.38",
                "nstream": "1",
                "port": "7161",
                "rate_KBps": "8097.65",
                "rate_Mbps": "66.3359",
                "real_seconds": "360.31",
                "receive_window_avail": "43690",
                "receive_window_size": "87380",
                "send_window_avail": "12020",
                "send_window_size": "24040",
                "stats": "cpu",
                "swaps": "928480+50csw",
                "system": "7.9",
                "user": "0.3"
            },
            "tx": {
                "buflen": "65536",
                "calls_per_sec": "126.64",
                "connect": "192.168.46.11",
                "cpu": "0%",
                "elapsed": "6:00",
                "host": "192.168.46.11",
                "io": "0+3pf",
                "io_calls": "45589",
                "megabytes": "2849.2538",
                "memory": "0i+0d-778maxrss",
                "mode": "tcp",
                "msec_per_call": "8.09",
                "mss": "1448",
                "nstream": "1",
                "port": "7161",
                "rate_KBps": "8104.54",
                "rate_Mbps": "66.3924",
                "real_seconds": "360.00",
                "receive_window_avail": "43690",
                "receive_window_size": "87380",
                "retrans": "0",
                "rtt_ms": "3.139",
                "send_window_avail": "12020",
                "send_window_size": "24040",
                "stats": "cpu",
                "swaps": "2135+1csw",
                "system": "1.4",
                "time_limit": "360.00",
                "user": "0.0"
            }
        },
        "conn_6": {
            "rx": {
                "KB_per_cpu_second": "404814.47",
                "accept": "192.168.46.15",
                "buflen": "65536",
                "calls_per_sec": "1824.01",
                "cpu": "1%",
                "cpu_seconds": "4.88",
                "elapsed": "6:00",
                "io": "0+18pf",
                "io_calls": "657347",
                "megabytes": "1930.8958",
                "memory": "0i+0d-298maxrss",
                "mode": "tcp",
                "msec_per_call": "0.56",
                "nstream": "1",
                "port": "7241",
                "rate_KBps": "5486.44",
                "rate_Mbps": "44.9449",
                "real_seconds": "360.39",
                "receive_window_avail": "43690",
                "receive_window_size": "87380",
                "send_window_avail": "12020",
                "send_window_size": "24040",
                "stats": "cpu",
                "swaps": "639705+66csw",
                "system": "4.7",
                "user": "0.1"
            },
            "tx": {
                "buflen": "65536",
                "calls_per_sec": "85.82",
                "connect": "192.168.46.11",
                "cpu": "0%",
                "elapsed": "6:00",
                "host": "192.168.46.11",
                "io": "0+3pf",
                "io_calls": "30895",
                "megabytes": "1930.8958",
                "memory": "0i+0d-782maxrss",
                "mode": "tcp",
                "msec_per_call": "11.93",
                "mss": "1448",
                "nstream": "1",
                "port": "7241",
                "rate_KBps": "5492.33",
                "rate_Mbps": "44.9931",
                "real_seconds": "360.00",
                "receive_window_avail": "43690",
                "receive_window_size": "87380",
                "retrans": "0",
                "rtt_ms": "2.563",
                "send_window_avail": "12020",
                "send_window_size": "24040",
                "stats": "cpu",
                "swaps": "1449+50csw",
                "system": "0.8",
                "time_limit": "360.00",
                "user": "0.0"
            }
        },
        "conn_7": {
            "rx": {
                "KB_per_cpu_second": "412589.94",
                "accept": "192.168.46.15",
                "buflen": "65536",
                "calls_per_sec": "1851.87",
                "cpu": "1%",
                "cpu_seconds": "4.93",
                "elapsed": "6:00",
                "io": "0+18pf",
                "io_calls": "667448",
                "megabytes": "1985.7128",
                "memory": "0i+0d-300maxrss",
                "mode": "tcp",
                "msec_per_call": "0.55",
                "nstream": "1",
                "port": "7101",
                "rate_KBps": "5641.70",
                "rate_Mbps": "46.2168",
                "real_seconds": "360.42",
                "receive_window_avail": "43690",
                "receive_window_size": "87380",
                "send_window_avail": "12020",
                "send_window_size": "24040",
                "stats": "cpu",
                "swaps": "650280+93csw",
                "system": "4.8",
                "user": "0.1"
            },
            "tx": {
                "buflen": "65536",
                "calls_per_sec": "88.26",
                "connect": "192.168.46.11",
                "cpu": "0%",
                "elapsed": "6:00",
                "host": "192.168.46.11",
                "io": "0+3pf",
                "io_calls": "31772",
                "megabytes": "1985.7128",
                "memory": "0i+0d-780maxrss",
                "mode": "tcp",
                "msec_per_call": "11.60",
                "mss": "1448",
                "nstream": "1",
                "port": "7101",
                "rate_KBps": "5648.25",
                "rate_Mbps": "46.2705",
                "real_seconds": "360.00",
                "receive_window_avail": "43690",
                "receive_window_size": "87380",
                "retrans": "0",
                "rtt_ms": "0.228",
                "send_window_avail": "12020",
                "send_window_size": "24040",
                "stats": "cpu",
                "swaps": "1493+7csw",
                "system": "0.9",
                "time_limit": "360.00",
                "user": "0.0"
            }
        },
        "conn_8": {
            "rx": {
                "KB_per_cpu_second": "344412.67",
                "accept": "192.168.46.15",
                "buflen": "65536",
                "calls_per_sec": "1733.60",
                "cpu": "1%",
                "cpu_seconds": "5.54",
                "elapsed": "6:00",
                "io": "0+18pf",
                "io_calls": "624626",
                "megabytes": "1864.7881",
                "memory": "0i+0d-300maxrss",
                "mode": "tcp",
                "msec_per_call": "0.59",
                "nstream": "1",
                "port": "7151",
                "rate_KBps": "5299.78",
                "rate_Mbps": "43.4158",
                "real_seconds": "360.31",
                "receive_window_avail": "43690",
                "receive_window_size": "87380",
                "send_window_avail": "12020",
                "send_window_size": "24040",
                "stats": "cpu",
                "swaps": "609351+4csw",
                "system": "5.1",
                "user": "0.3"
            },
            "tx": {
                "buflen": "65536",
                "calls_per_sec": "82.88",
                "connect": "192.168.46.11",
                "cpu": "0%",
                "elapsed": "6:00",
                "host": "192.168.46.11",
                "io": "0+3pf",
                "io_calls": "29837",
                "megabytes": "1864.7881",
                "memory": "0i+0d-780maxrss",
                "mode": "tcp",
                "msec_per_call": "12.36",
                "mss": "1448",
                "nstream": "1",
                "port": "7151",
                "rate_KBps": "5304.29",
                "rate_Mbps": "43.4527",
                "real_seconds": "360.00",
                "receive_window_avail": "43690",
                "receive_window_size": "87380",
                "retrans": "0",
                "rtt_ms": "11.401",
                "send_window_avail": "12020",
                "send_window_size": "24040",
                "stats": "cpu",
                "swaps": "1393+2csw",
                "system": "0.9",
                "time_limit": "360.00",
                "user": "0.0"
            }
        },
        "conn_9": {
            "rx": {
                "KB_per_cpu_second": "384627.55",
                "accept": "192.168.46.15",
                "buflen": "65536",
                "calls_per_sec": "2599.31",
                "cpu": "2%",
                "cpu_seconds": "7.39",
                "elapsed": "6:00",
                "io": "0+18pf",
                "io_calls": "936735",
                "megabytes": "2776.7037",
                "memory": "0i+0d-298maxrss",
                "mode": "tcp",
                "msec_per_call": "0.39",
                "nstream": "1",
                "port": "7171",
                "rate_KBps": "7889.88",
                "rate_Mbps": "64.6339",
                "real_seconds": "360.38",
                "receive_window_avail": "43690",
                "receive_window_size": "87380",
                "send_window_avail": "12020",
                "send_window_size": "24040",
                "stats": "cpu",
                "swaps": "905973+53csw",
                "system": "7.0",
                "user": "0.3"
            },
            "tx": {
                "buflen": "65536",
                "calls_per_sec": "123.41",
                "connect": "192.168.46.11",
                "cpu": "0%",
                "elapsed": "6:00",
                "host": "192.168.46.11",
                "io": "0+3pf",
                "io_calls": "44428",
                "megabytes": "2776.7037",
                "memory": "0i+0d-780maxrss",
                "mode": "tcp",
                "msec_per_call": "8.30",
                "mss": "1448",
                "nstream": "1",
                "port": "7171",
                "rate_KBps": "7898.18",
                "rate_Mbps": "64.7019",
                "real_seconds": "360.00",
                "receive_window_avail": "43690",
                "receive_window_size": "87380",
                "retrans": "0",
                "rtt_ms": "1.444",
                "send_window_avail": "12020",
                "send_window_size": "24040",
                "stats": "cpu",
                "swaps": "2090+1csw",
                "system": "1.4",
                "time_limit": "360.00",
                "user": "0.0"
            }
        }
    },
    "concurrent": 15,
    "name": "BTC bigfoot2 bigfoot6 360 seconds, 15 concurrency",
    "receiver": "venzano@192.168.46.11",
    "senders": "venzano@192.168.46.15",
    "state_receiver": {
        "buffers": "217652",
        "cached": "1168828",
        "kernel_version": "3.2.0-49-generic",
        "load_1": "0.16",
        "load_15": "0.22",
        "load_5": "0.14",
        "mem_free": "128870920",
        "mem_total": "131992032",
        "net_eth0": {
            "bytes_inS": "1047.40",
            "bytes_outS": "1325.80",
            "errors_inS": "0.00",
            "errors_outS": "0.00",
            "packets_inS": "6.80",
            "packets_outS": "8.80"
        },
        "net_gre_if0": {
            "bytes_inS": "0.00",
            "bytes_outS": "0.00",
            "errors_inS": "0.00",
            "errors_outS": "0.00",
            "packets_inS": "0.00",
            "packets_outS": "0.00"
        },
        "net_lo": {
            "bytes_inS": "0.00",
            "bytes_outS": "0.00",
            "errors_inS": "0.00",
            "errors_outS": "0.00",
            "packets_inS": "0.00",
            "packets_outS": "0.00"
        },
        "net_total": {
            "bytes_inS": "1047.40",
            "bytes_outS": "1325.80",
            "errors_inS": "0.00",
            "errors_outS": "0.00",
            "packets_inS": "6.80",
            "packets_outS": "8.80"
        },
        "processes": "1/346",
        "slab_reclaimable": "127828",
        "slab_total": "204576",
        "slab_unreclaimed": "76748",
        "swap_free": "0",
        "swap_total": "0"
    },
    "state_sender": {
        "buffers": "336556",
        "cached": "8385008",
        "kernel_version": "3.2.0-49-generic",
        "load_1": "0.26",
        "load_15": "0.15",
        "load_5": "0.16",
        "mem_free": "121143652",
        "mem_total": "131992032",
        "net_eth0": {
            "bytes_inS": "2516.00",
            "bytes_outS": "7554.60",
            "errors_inS": "0.00",
            "errors_outS": "0.00",
            "packets_inS": "9.60",
            "packets_outS": "17.60"
        },
        "net_lo": {
            "bytes_inS": "140.00",
            "bytes_outS": "140.00",
            "errors_inS": "0.00",
            "errors_outS": "0.00",
            "packets_inS": "0.80",
            "packets_outS": "0.80"
        },
        "net_total": {
            "bytes_inS": "2656.00",
            "bytes_outS": "7694.60",
            "errors_inS": "0.00",
            "errors_outS": "0.00",
            "packets_inS": "10.40",
            "packets_outS": "18.40"
        },
        "processes": "1/347",
        "slab_reclaimable": "366136",
        "slab_total": "454376",
        "slab_unreclaimed": "88240",
        "swap_free": "0",
        "swap_total": "0"
    },
    "time": 1375275530.799719,
    "type": "BTC"
}