{"vm1": {"vm1:m22": [{"cpu_time": "809", "name": "vm1:m22:th0", "wall_time_start": "1407932781169", "bytes": "3355443201", "time_elapsed": "23752", "peer_name": "vm1:r0"}], "vm1:m23": [{"cpu_time": "803", "name": "vm1:m23:th0", "wall_time_start": "1407932781163", "bytes": "3355443201", "time_elapsed": "23635", "peer_name": "vm1:r0"}], "vm1:m20": [{"cpu_time": "787", "name": "vm1:m20:th0", "wall_time_start": "1407932781162", "bytes": "3355443201", "time_elapsed": "23717", "peer_name": "vm1:r0"}], "vm1:m21": [{"cpu_time": "796", "name": "vm1:m21:th0", "wall_time_start": "1407932781163", "bytes": "3355443201", "time_elapsed": "23520", "peer_name": "vm1:r0"}], "vm1:m26": [{"cpu_time": "782", "name": "vm1:m26:th0", "wall_time_start": "1407932781169", "bytes": "3355443201", "time_elapsed": "23521", "peer_name": "vm1:r0"}], "vm1:m27": [{"cpu_time": "803", "name": "vm1:m27:th0", "wall_time_start": "1407932781171", "bytes": "3355443201", "time_elapsed": "23712", "peer_name": "vm1:r0"}], "vm1:m24": [{"cpu_time": "804", "name": "vm1:m24:th0", "wall_time_start": "1407932781164", "bytes": "3355443201", "time_elapsed": "23665", "peer_name": "vm1:r0"}], "vm1:m25": [{"cpu_time": "800", "name": "vm1:m25:th0", "wall_time_start": "1407932781170", "bytes": "3355443201", "time_elapsed": "23229", "peer_name": "vm1:r0"}], "vm1:m28": [{"cpu_time": "789", "name": "vm1:m28:th0", "wall_time_start": "1407932781169", "bytes": "3355443201", "time_elapsed": "23728", "peer_name": "vm1:r0"}], "vm1:m29": [{"cpu_time": "799", "name": "vm1:m29:th0", "wall_time_start": "1407932781170", "bytes": "3355443201", "time_elapsed": "23330", "peer_name": "vm1:r0"}], "vm1:m3": [{"cpu_time": "790", "name": "vm1:m3:th0", "wall_time_start": "1407932781150", "bytes": "3355443201", "time_elapsed": "23729", "peer_name": "vm1:r0"}], "vm1:m2": [{"cpu_time": "815", "name": "vm1:m2:th0", "wall_time_start": "1407932781150", "bytes": "3355443201", "time_elapsed": "23689", "peer_name": "vm1:r0"}], "vm1:m1": [{"cpu_time": "798", "name": "vm1:m1:th0", "wall_time_start": "1407932781151", "bytes": "3355443201", "time_elapsed": "23664", "peer_name": "vm1:r0"}], "vm1:m0": [{"cpu_time": "800", "name": "vm1:m0:th0", "wall_time_start": "1407932781152", "bytes": "3355443201", "time_elapsed": "23715", "peer_name": "vm1:r0"}], "vm1:m7": [{"cpu_time": "788", "name": "vm1:m7:th0", "wall_time_start": "1407932781154", "bytes": "3355443201", "time_elapsed": "23620", "peer_name": "vm1:r0"}], "vm1:m6": [{"cpu_time": "798", "name": "vm1:m6:th0", "wall_time_start": "1407932781154", "bytes": "3355443201", "time_elapsed": "23597", "peer_name": "vm1:r0"}], "vm1:m5": [{"cpu_time": "798", "name": "vm1:m5:th0", "wall_time_start": "1407932781154", "bytes": "3355443201", "time_elapsed": "23625", "peer_name": "vm1:r0"}], "vm1:m4": [{"cpu_time": "797", "name": "vm1:m4:th0", "wall_time_start": "1407932781152", "bytes": "3355443201", "time_elapsed": "23508", "peer_name": "vm1:r0"}], "vm1:m9": [{"cpu_time": "786", "name": "vm1:m9:th0", "wall_time_start": "1407932781154", "bytes": "3355443201", "time_elapsed": "23606", "peer_name": "vm1:r0"}], "vm1:m8": [{"cpu_time": "814", "name": "vm1:m8:th0", "wall_time_start": "1407932781155", "bytes": "3355443201", "time_elapsed": "23378", "peer_name": "vm1:r0"}], "vm1:r0": [{"cpu_time": "2827", "name": "vm1:r0:th0:0", "wall_time_start": "1407932781149", "bytes": "3355443201", "time_elapsed": "23731", "peer_name": "vm1:m0"}, {"cpu_time": "2815", "name": "vm1:r0:th1:0", "wall_time_start": "1407932781150", "bytes": "3355443201", "time_elapsed": "23688", "peer_name": "vm1:m1"}, {"cpu_time": "2836", "name": "vm1:r0:th2:0", "wall_time_start": "1407932781150", "bytes": "3355443201", "time_elapsed": "23708", "peer_name": "vm1:m2"}, {"cpu_time": "2804", "name": "vm1:r0:th3:0", "wall_time_start": "1407932781150", "bytes": "3355443201", "time_elapsed": "23742", "peer_name": "vm1:m3"}, {"cpu_time": "2783", "name": "vm1:r0:th4:0", "wall_time_start": "1407932781150", "bytes": "3355443201", "time_elapsed": "23545", "peer_name": "vm1:m4"}, {"cpu_time": "2795", "name": "vm1:r0:th5:0", "wall_time_start": "1407932781152", "bytes": "3355443201", "time_elapsed": "23665", "peer_name": "vm1:m5"}, {"cpu_time": "2797", "name": "vm1:r0:th6:0", "wall_time_start": "1407932781153", "bytes": "3355443201", "time_elapsed": "23644", "peer_name": "vm1:m6"}, {"cpu_time": "2812", "name": "vm1:r0:th7:0", "wall_time_start": "1407932781153", "bytes": "3355443201", "time_elapsed": "23662", "peer_name": "vm1:m7"}, {"cpu_time": "2814", "name": "vm1:r0:th8:0", "wall_time_start": "1407932781154", "bytes": "3355443201", "time_elapsed": "23436", "peer_name": "vm1:m8"}, {"cpu_time": "2787", "name": "vm1:r0:th9:0", "wall_time_start": "1407932781154", "bytes": "3355443201", "time_elapsed": "23658", "peer_name": "vm1:m9"}, {"cpu_time": "2798", "name": "vm1:r0:th10:0", "wall_time_start": "1407932781155", "bytes": "3355443201", "time_elapsed": "23625", "peer_name": "vm1:m10"}, {"cpu_time": "2796", "name": "vm1:r0:th11:0", "wall_time_start": "1407932781156", "bytes": "3355443201", "time_elapsed": "23580", "peer_name": "vm1:m11"}, {"cpu_time": "2792", "name": "vm1:r0:th12:0", "wall_time_start": "1407932781157", "bytes": "3355443201", "time_elapsed": "23749", "peer_name": "vm1:m12"}, {"cpu_time": "2781", "name": "vm1:r0:th13:0", "wall_time_start": "1407932781157", "bytes": "3355443201", "time_elapsed": "23581", "peer_name": "vm1:m13"}, {"cpu_time": "2777", "name": "vm1:r0:th14:0", "wall_time_start": "1407932781158", "bytes": "3355443201", "time_elapsed": "23412", "peer_name": "vm1:m14"}, {"cpu_time": "2828", "name": "vm1:r0:th15:0", "wall_time_start": "1407932781159", "bytes": "3355443201", "time_elapsed": "23590", "peer_name": "vm1:m15"}, {"cpu_time": "2795", "name": "vm1:r0:th16:0", "wall_time_start": "1407932781160", "bytes": "3355443201", "time_elapsed": "23664", "peer_name": "vm1:m16"}, {"cpu_time": "2826", "name": "vm1:r0:th17:0", "wall_time_start": "1407932781160", "bytes": "3355443201", "time_elapsed": "23749", "peer_name": "vm1:m17"}, {"cpu_time": "2786", "name": "vm1:r0:th18:0", "wall_time_start": "1407932781160", "bytes": "3355443201", "time_elapsed": "23619", "peer_name": "vm1:m18"}, {"cpu_time": "2790", "name": "vm1:r0:th19:0", "wall_time_start": "1407932781160", "bytes": "3355443201", "time_elapsed": "23613", "peer_name": "vm1:m19"}, {"cpu_time": "2800", "name": "vm1:r0:th20:0", "wall_time_start": "1407932781160", "bytes": "3355443201", "time_elapsed": "23731", "peer_name": "vm1:m20"}, {"cpu_time": "2775", "name": "vm1:r0:th21:0", "wall_time_start": "1407932781161", "bytes": "3355443201", "time_elapsed": "23570", "peer_name": "vm1:m21"}, {"cpu_time": "2818", "name": "vm1:r0:th22:0", "wall_time_start": "1407932781162", "bytes": "3355443201", "time_elapsed": "23762", "peer_name": "vm1:m22"}, {"cpu_time": "2800", "name": "vm1:r0:th23:0", "wall_time_start": "1407932781163", "bytes": "3355443201", "time_elapsed": "23663", "peer_name": "vm1:m23"}, {"cpu_time": "2836", "name": "vm1:r0:th24:0", "wall_time_start": "1407932781163", "bytes": "3355443201", "time_elapsed": "23686", "peer_name": "vm1:m24"}, {"cpu_time": "2779", "name": "vm1:r0:th25:0", "wall_time_start": "1407932781163", "bytes": "3355443201", "time_elapsed": "23294", "peer_name": "vm1:m25"}, {"cpu_time": "2771", "name": "vm1:r0:th26:0", "wall_time_start": "1407932781163", "bytes": "3355443201", "time_elapsed": "23563", "peer_name": "vm1:m26"}, {"cpu_time": "2805", "name": "vm1:r0:th27:0", "wall_time_start": "1407932781163", "bytes": "3355443201", "time_elapsed": "23732", "peer_name": "vm1:m27"}, {"cpu_time": "2797", "name": "vm1:r0:th28:0", "wall_time_start": "1407932781164", "bytes": "3355443201", "time_elapsed": "23742", "peer_name": "vm1:m28"}, {"cpu_time": "2788", "name": "vm1:r0:th29:0", "wall_time_start": "1407932781165", "bytes": "3355443201", "time_elapsed": "23388", "peer_name": "vm1:m29"}, {"cpu_time": "2825", "name": "vm1:r0:th30:0", "wall_time_start": "1407932781165", "bytes": "3355443201", "time_elapsed": "23749", "peer_name": "vm1:m30"}, {"cpu_time": "2820", "name": "vm1:r0:th31:0", "wall_time_start": "1407932781166", "bytes": "3355443201", "time_elapsed": "23725", "peer_name": "vm1:m31"}], "vm1:m31": [{"cpu_time": "802", "name": "vm1:m31:th0", "wall_time_start": "1407932781167", "bytes": "3355443201", "time_elapsed": "23701", "peer_name": "vm1:r0"}], "vm1:m30": [{"cpu_time": "797", "name": "vm1:m30:th0", "wall_time_start": "1407932781170", "bytes": "3355443201", "time_elapsed": "23740", "peer_name": "vm1:r0"}], "vm1:m19": [{"cpu_time": "791", "name": "vm1:m19:th0", "wall_time_start": "1407932781172", "bytes": "3355443201", "time_elapsed": "23556", "peer_name": "vm1:r0"}], "vm1:m18": [{"cpu_time": "788", "name": "vm1:m18:th0", "wall_time_start": "1407932781163", "bytes": "3355443201", "time_elapsed": "23574", "peer_name": "vm1:r0"}], "vm1:m13": [{"cpu_time": "802", "name": "vm1:m13:th0", "wall_time_start": "1407932781160", "bytes": "3355443201", "time_elapsed": "23523", "peer_name": "vm1:r0"}], "vm1:m12": [{"cpu_time": "786", "name": "vm1:m12:th0", "wall_time_start": "1407932781157", "bytes": "3355443201", "time_elapsed": "23742", "peer_name": "vm1:r0"}], "vm1:m11": [{"cpu_time": "792", "name": "vm1:m11:th0", "wall_time_start": "1407932781157", "bytes": "3355443201", "time_elapsed": "23528", "peer_name": "vm1:r0"}], "vm1:m10": [{"cpu_time": "799", "name": "vm1:m10:th0", "wall_time_start": "1407932781155", "bytes": "3355443201", "time_elapsed": "23583", "peer_name": "vm1:r0"}], "vm1:m17": [{"cpu_time": "816", "name": "vm1:m17:th0", "wall_time_start": "1407932781162", "bytes": "3355443201", "time_elapsed": "23740", "peer_name": "vm1:r0"}], "vm1:m16": [{"cpu_time": "812", "name": "vm1:m16:th0", "wall_time_start": "1407932781162", "bytes": "3355443201", "time_elapsed": "23625", "peer_name": "vm1:r0"}], "vm1:m15": [{"cpu_time": "808", "name": "vm1:m15:th0", "wall_time_start": "1407932781164", "bytes": "3355443201", "time_elapsed": "23532", "peer_name": "vm1:r0"}], "vm1:m14": [{"cpu_time": "790", "name": "vm1:m14:th0", "wall_time_start": "1407932781160", "bytes": "3355443201", "time_elapsed": "23354", "peer_name": "vm1:r0"}]}}